README.txt
setup.py
./reverse_geocoder/__init__.py
./reverse_geocoder/cKDTree_MP.py
./reverse_geocoder/rg_cities1000.csv
reverse_geocoder.egg-info/PKG-INFO
reverse_geocoder.egg-info/SOURCES.txt
reverse_geocoder.egg-info/dependency_links.txt
reverse_geocoder.egg-info/requires.txt
reverse_geocoder.egg-info/top_level.txt