Metadata-Version: 1.0
Name: reverse-geocoder
Version: 1.5
Summary: Fast, offline reverse geocoder
Home-page: https://github.com/thampiman/reverse-geocoder
Author: Ajay Thampi
Author-email: ajay.thampi@gmail.com
License: lgpl
Platform: UNKNOWN
